binwalk/__init__.py
binwalk/__version__.py
binwalk/_v3_backend.py
binwalk/py.typed
binwalk/binwalk_bin/BUILD_NOTE.md
binwalk/binwalk_bin/README.md
binwalk/binwalk_bin/__init__.py
binwalk/binwalk_bin/binwalk_windows_x64.exe
binwalk/core/__init__.py
binwalk/core/module.py
binwalk3-3.1.3.dist-info/licenses/LICENSE
binwalk3-3.1.3.dist-info/METADATA
binwalk3-3.1.3.dist-info/WHEEL
binwalk3-3.1.3.dist-info/top_level.txt
binwalk3-3.1.3.dist-info/RECORD
