Metadata-Version: 2.4
Name: binwalk3
Version: 3.1.3
Summary: Binwalk v3 with v2-compatible Python API - Fast firmware analysis
Author-email: Zachary Flint <zach.flint2@gmail.com>
License: MIT
Project-URL: Homepage, https://github.com/zacharyflint/binwalk3
Project-URL: Repository, https://github.com/zacharyflint/binwalk3
Project-URL: Issues, https://github.com/zacharyflint/binwalk3/issues
Project-URL: Documentation, https://github.com/zacharyflint/binwalk3/blob/main/README.md
Project-URL: Changelog, https://github.com/zacharyflint/binwalk3/blob/main/CHANGELOG.md
Keywords: binwalk,firmware,analysis,reverse-engineering,security,binary-analysis,embedded,iot
Classifier: Development Status :: 4 - Beta
Classifier: Intended Audience :: Developers
Classifier: Intended Audience :: Information Technology
Classifier: Intended Audience :: Science/Research
Classifier: Topic :: Security
Classifier: Topic :: Software Development :: Disassemblers
Classifier: Topic :: System :: Filesystems
Classifier: Programming Language :: Python :: 3
Classifier: Programming Language :: Python :: 3.8
Classifier: Programming Language :: Python :: 3.9
Classifier: Programming Language :: Python :: 3.10
Classifier: Programming Language :: Python :: 3.11
Classifier: Programming Language :: Python :: 3.12
Classifier: Programming Language :: Python :: 3.13
Classifier: Operating System :: OS Independent
Classifier: License :: OSI Approved :: MIT License
Requires-Python: >=3.8
License-File: LICENSE
Dynamic: license-file
